flask_sharething/__init__.py
flask_sharething/babel.py
flask_sharething/bcrypt.py
flask_sharething/cache.py
flask_sharething/flask_redis.py
flask_sharething/login.py
flask_sharething/mail.py
flask_sharething/migrate.py
flask_sharething/oauth.py
flask_sharething/redis.py
flask_sharething/restful.py
flask_sharething/sqlalchemy.py
flask_sharething/user.py
flask_sharething-0.3.0.dist-info/LICENSE
flask_sharething-0.3.0.dist-info/METADATA
flask_sharething-0.3.0.dist-info/WHEEL
flask_sharething-0.3.0.dist-info/top_level.txt
flask_sharething-0.3.0.dist-info/RECORD
