Metadata-Version: 2.1
Name: flask-sharething
Version: 0.3.0
Summary: Share extensions in multiple flask sub-applications
Home-page: https://github.com/qileroro/flask-sharething/
Author: Kevin Wong
Author-email: qileroro@qq.com
License: Apache License, Version 2.0
Platform: UNKNOWN
Classifier: Development Status :: 3 - Alpha
Classifier: License :: OSI Approved :: BSD License
Classifier: Programming Language :: Python :: 3.7
